bentoutils/__init__.py
bentoutils/cli.py
bentoutils/kubeutil.py
bentoutils/print_bento_manifest.py
bentoutils/print_kaniko_manifest.py
bentoutils/print_knative_manifest.py
bentoutils/print_route_manifest.py
bentoutils-1.1.2.dist-info/METADATA
bentoutils-1.1.2.dist-info/WHEEL
bentoutils-1.1.2.dist-info/entry_points.txt
bentoutils-1.1.2.dist-info/top_level.txt
bentoutils-1.1.2.dist-info/RECORD
