Metadata-Version: 2.1
Name: bentoutils
Version: 1.1.2
Summary: Utilities for working with BentoML V1.x
Home-page: https://github.com/markmo/bentoutils
Author: Mark Moloney
Author-email: m4rkmo@gmail.com
License: UNKNOWN
Platform: UNKNOWN
Classifier: Programming Language :: Python :: 3
Classifier: License :: OSI Approved :: MIT License
Classifier: Operating System :: OS Independent
Requires-Python: >=3.6
Requires-Dist: BentoML
Requires-Dist: boto3
Requires-Dist: click
Requires-Dist: kubernetes (==11.0.0)
Requires-Dist: PyYAML
Requires-Dist: stringcase
Requires-Dist: text-unidecode
